dlt_plus/__init__.py
dlt_plus/current.py
dlt_plus/plugin.py
dlt_plus/py.typed
dlt_plus/version.py
dlt_plus/_runner/__init__.py
dlt_plus/_runner/exceptions.py
dlt_plus/_runner/pipeline_runner.py
dlt_plus/_runner/plus_log_collector.py
dlt_plus/_runner/prefect_collector.py
dlt_plus/_runner/prefect_helpers.py
dlt_plus/_runner/trace_helpers.py
dlt_plus/_runner/trace_resource.py
dlt_plus/_runner/utils.py
dlt_plus/cache/__init__.py
dlt_plus/cache/cache.py
dlt_plus/cache/cli.py
dlt_plus/cache/config.py
dlt_plus/common/__init__.py
dlt_plus/common/cli.py
dlt_plus/common/constants.py
dlt_plus/common/exceptions.py
dlt_plus/common/configuration/__init__.py
dlt_plus/common/configuration/providers.py
dlt_plus/common/license/__init__.py
dlt_plus/common/license/cli.py
dlt_plus/common/license/decorators.py
dlt_plus/common/license/exceptions.py
dlt_plus/common/license/license.py
dlt_plus/dbt_generator/__init__.py
dlt_plus/dbt_generator/cli.py
dlt_plus/dbt_generator/config.py
dlt_plus/dbt_generator/exceptions.py
dlt_plus/dbt_generator/render.py
dlt_plus/dbt_generator/types.py
dlt_plus/dbt_generator/utils.py
dlt_plus/dbt_generator/templates/README.md.j2
dlt_plus/dbt_generator/templates/dbt_project.yml.j2
dlt_plus/dbt_generator/templates/main.py.j2
dlt_plus/dbt_generator/templates/requirements.txt.j2
dlt_plus/dbt_generator/templates/sources.yml.j2
dlt_plus/dbt_generator/templates/table_active_load_ids.sql.j2
dlt_plus/dbt_generator/templates/table_fact.sql.j2
dlt_plus/dbt_generator/templates/table_mart.sql.j2
dlt_plus/dbt_generator/templates/table_processed_load_ids.sql.j2
dlt_plus/dbt_generator/templates/table_staging.sql.j2
dlt_plus/destinations/__init__.py
dlt_plus/destinations/adapters.py
dlt_plus/destinations/dataset.py
dlt_plus/destinations/utils.py
dlt_plus/destinations/impl/__init__.py
dlt_plus/destinations/impl/filesystem/__init__.py
dlt_plus/destinations/impl/filesystem/factory.py
dlt_plus/destinations/impl/iceberg/README.md
dlt_plus/destinations/impl/iceberg/__init__.py
dlt_plus-0.17.0.dist-info/METADATA
dlt_plus-0.17.0.dist-info/WHEEL
dlt_plus-0.17.0.dist-info/entry_points.txt
dlt_plus-0.17.0.dist-info/licenses/LICENSE.md
dlt_plus-0.17.0.dist-info/RECORD
